leakrfc/__init__.py
leakrfc/api/__init__.py
leakrfc/api/auth.py
leakrfc/api/main.py
leakrfc/api/util.py
leakrfc/archive/__init__.py
leakrfc/archive/base.py
leakrfc/archive/cache.py
leakrfc/archive/dataset.py
leakrfc/archive/documents.py
leakrfc/cli.py
leakrfc/connectors/aleph.py
leakrfc/crawl.py
leakrfc/exceptions.py
leakrfc/export.py
leakrfc/extract.py
leakrfc/import.py
leakrfc/logging.py
leakrfc/make.py
leakrfc/model.py
leakrfc/settings.py
leakrfc/sync/__init__.py
leakrfc/sync/aleph.py
leakrfc/sync/aleph_entities.py
leakrfc/sync/memorious.py
leakrfc/util.py
leakrfc/worker.py
leakrfc-0.0.4.dist-info/LICENSE
leakrfc-0.0.4.dist-info/METADATA
leakrfc-0.0.4.dist-info/NOTICE
leakrfc-0.0.4.dist-info/WHEEL
leakrfc-0.0.4.dist-info/entry_points.txt
leakrfc-0.0.4.dist-info/RECORD
