Metadata-Version: 2.3
Name: leakrfc
Version: 0.0.4
Summary: Data standard, storage and retrieval for leaks and document collections
License: AGPLv3+
Author: Simon Wörpel
Author-email: simon.woerpel@pm.me
Requires-Python: >=3.11,<4
Classifier: License :: OSI Approved :: GNU Affero General Public License v3 or later (AGPLv3+)
Classifier: Intended Audience :: Developers
Classifier: Operating System :: OS Independent
Classifier: Programming Language :: Python
Classifier: Programming Language :: Python :: 3.11
Classifier: Programming Language :: Python :: 3.12
Classifier: Programming Language :: Python :: 3.13
Provides-Extra: api
Requires-Dist: alephclient (>=2.6.0,<3.0.0)
Requires-Dist: anystore (>=0.3.0,<0.4.0)
Requires-Dist: fastapi (>=0.115.6,<0.116.0) ; extra == "api"
Requires-Dist: ftmq (>=0.8.0,<0.9.0)
Requires-Dist: jinja2 (>=3.1.5,<4.0.0)
Requires-Dist: pandas (>=2.2.3,<3.0.0)
Requires-Dist: patool (>=3.1.0,<4.0.0)
Requires-Dist: pyjwt (>=2.10.1,<3.0.0) ; extra == "api"
Requires-Dist: rich (>=13.9.4,<14.0.0)
Requires-Dist: structlog (>=24.4.0,<25.0.0)
Requires-Dist: uvicorn (>=0.34.0,<0.35.0) ; extra == "api"
Project-URL: Documentation, https://docs.investigraph.dev/lib/leakrfc
Project-URL: Homepage, https://docs.investigraph.dev/lib/leakrfc
Project-URL: Issues, https://github.com/investigativedata/leakrfc/issues
Project-URL: Repository, https://github.com/investigativedata/leakrfc
